stkutils/__init__.py
stkutils/all_spawn.py
stkutils/binary_data.py
stkutils/chunked.py
stkutils/conf.py
stkutils/convert.py
stkutils/core.py
stkutils/data_packet.py
stkutils/gg_version.py
stkutils/ini_file.py
stkutils/perl_utils.py
stkutils/scan_test.py
stkutils/stkutils_math.py
stkutils/utils.py
stkutils/file/__init__.py
stkutils/file/entity.py
stkutils/file/graph.py
stkutils/file/ogf.py
stkutils/file/texture_thumbnail.py
stkutils/level/__init__.py
stkutils/level/level.py
stkutils/level/level_ai.py
stkutils/level/level_cform.py
stkutils/level/level_details.py
stkutils/level/level_fog_vol.py
stkutils/level/level_game.py
stkutils/level/level_gct.py
stkutils/level/level_geom.py
stkutils/level/level_ps_static.py
stkutils/level/level_snd_static.py
stkutils/xr/gamemtl_xr.py
stkutils/xr/lanims_xr.py
stkutils/xr/particles_xr.py
stkutils/xr/senvironment_xr.py
stkutils/xr/shaders_xr.py
stkutils/xr/shaders_xrlc_xr.py
stkutils-0.2.3.dist-info/METADATA
stkutils-0.2.3.dist-info/WHEEL
stkutils-0.2.3.dist-info/top_level.txt
stkutils-0.2.3.dist-info/RECORD
